{
    "items": [
      {
        "name": "V_aDi_M",
        "id": 15950,
        "uniqueUrlName": null,
        "photos": {
          "small": null,
          "large": null
        },
        "status": null,
        "followed": false
      },
      {
        "name": "AlexFox",
        "id": 15949,
        "uniqueUrlName": null,
        "photos": {
          "small": null,
          "large": null
        },
        "status": null,
        "followed": false
      },
      {
        "name": "D3adduck",
        "id": 15948,
        "uniqueUrlName": null,
        "photos": {
          "small": null,
          "large": null
        },
        "status": null,
        "followed": false
      },
      {
        "name": "sladmorkva",
        "id": 15947,
        "uniqueUrlName": null,
        "photos": {
          "small": null,
          "large": null
        },
        "status": null,
        "followed": false
      },
      {
        "name": "samesmile",
        "id": 15946,
        "uniqueUrlName": null,
        "photos": {
          "small": null,
          "large": null
        },
        "status": null,
        "followed": false
      },
      {
        "name": "tsake-love",
        "id": 15945,
        "uniqueUrlName": null,
        "photos": {
          "small": null,
          "large": null
        },
        "status": null,
        "followed": false
      },
      {
        "name": "test-lesson-61",
        "id": 15944,
        "uniqueUrlName": null,
        "photos": {
          "small": null,
          "large": null
        },
        "status": null,
        "followed": false
      },
      {
        "name": "massyk",
        "id": 15943,
        "uniqueUrlName": null,
        "photos": {
          "small": null,
          "large": null
        },
        "status": null,
        "followed": false
      },
      {
        "name": "WilliamsDy",
        "id": 15942,
        "uniqueUrlName": null,
        "photos": {
          "small": null,
          "large": null
        },
        "status": null,
        "followed": false
      },
      {
        "name": "FrankSon",
        "id": 15941,
        "uniqueUrlName": null,
        "photos": {
          "small": null,
          "large": null
        },
        "status": null,
        "followed": false
      },
      {
        "name": "test_login",
        "id": 15940,
        "uniqueUrlName": null,
        "photos": {
          "small": null,
          "large": null
        },
        "status": null,
        "followed": false
      },
      {
        "name": "Romochke",
        "id": 15939,
        "uniqueUrlName": null,
        "photos": {
          "small": null,
          "large": null
        },
        "status": null,
        "followed": false
      },
      {
        "name": "qwerty111222333",
        "id": 15938,
        "uniqueUrlName": null,
        "photos": {
          "small": null,
          "large": null
        },
        "status": null,
        "followed": false
      },
      {
        "name": "lmikon",
        "id": 15937,
        "uniqueUrlName": null,
        "photos": {
          "small": null,
          "large": null
        },
        "status": null,
        "followed": false
      },
      {
        "name": "asekach",
        "id": 15936,
        "uniqueUrlName": null,
        "photos": {
          "small": null,
          "large": null
        },
        "status": null,
        "followed": false
      },
      {
        "name": "r-grigoryan",
        "id": 15935,
        "uniqueUrlName": null,
        "photos": {
          "small": null,
          "large": null
        },
        "status": null,
        "followed": false
      },
      {
        "name": "sevilya99",
        "id": 15934,
        "uniqueUrlName": null,
        "photos": {
          "small": null,
          "large": null
        },
        "status": null,
        "followed": false
      },
      {
        "name": "DimonONE",
        "id": 15933,
        "uniqueUrlName": null,
        "photos": {
          "small": null,
          "large": null
        },
        "status": null,
        "followed": false
      },
      {
        "name": "Reikai1337",
        "id": 15932,
        "uniqueUrlName": null,
        "photos": {
          "small": null,
          "large": null
        },
        "status": null,
        "followed": false
      },
      {
        "name": "Acedia",
        "id": 15931,
        "uniqueUrlName": null,
        "photos": {
          "small": null,
          "large": null
        },
        "status": null,
        "followed": false
      },
      {
        "name": "Ntigl",
        "id": 15930,
        "uniqueUrlName": null,
        "photos": {
          "small": null,
          "large": null
        },
        "status": null,
        "followed": false
      },
      {
        "name": "towelie",
        "id": 15929,
        "uniqueUrlName": null,
        "photos": {
          "small": null,
          "large": null
        },
        "status": null,
        "followed": false
      },
      {
        "name": "mr_slave",
        "id": 15928,
        "uniqueUrlName": null,
        "photos": {
          "small": null,
          "large": null
        },
        "status": null,
        "followed": false
      },
      {
        "name": "antonC",
        "id": 15927,
        "uniqueUrlName": null,
        "photos": {
          "small": null,
          "large": null
        },
        "status": null,
        "followed": false
      },
      {
        "name": "SaBaTeuR",
        "id": 15926,
        "uniqueUrlName": null,
        "photos": {
          "small": null,
          "large": null
        },
        "status": null,
        "followed": false
      },
      {
        "name": "dpu99861",
        "id": 15925,
        "uniqueUrlName": null,
        "photos": {
          "small": null,
          "large": null
        },
        "status": "Хауди ХО ХО ХО",
        "followed": false
      },
      {
        "name": "0legg93",
        "id": 15924,
        "uniqueUrlName": null,
        "photos": {
          "small": null,
          "large": null
        },
        "status": null,
        "followed": false
      },
      {
        "name": "g4rfiEld",
        "id": 15923,
        "uniqueUrlName": null,
        "photos": {
          "small": null,
          "large": null
        },
        "status": null,
        "followed": false
      },
      {
        "name": "g4rfiEld2002",
        "id": 15922,
        "uniqueUrlName": null,
        "photos": {
          "small": null,
          "large": null
        },
        "status": null,
        "followed": false
      },
      {
        "name": "evgeniy2024",
        "id": 15921,
        "uniqueUrlName": null,
        "photos": {
          "small": null,
          "large": null
        },
        "status": null,
        "followed": false
      },
      {
        "name": "DimasYl",
        "id": 15920,
        "uniqueUrlName": null,
        "photos": {
          "small": null,
          "large": null
        },
        "status": null,
        "followed": false
      },
      {
        "name": "vhv",
        "id": 15919,
        "uniqueUrlName": null,
        "photos": {
          "small": "https://social-network.samuraijs.com/activecontent/images/users/15919/user-small.jpg?v=1",
          "large": "https://social-network.samuraijs.com/activecontent/images/users/15919/user.jpg?v=1"
        },
        "status": "Hello",
        "followed": false
      },
      {
        "name": "prowebit",
        "id": 15918,
        "uniqueUrlName": null,
        "photos": {
          "small": null,
          "large": null
        },
        "status": null,
        "followed": false
      },
      {
        "name": "m_allekssandr",
        "id": 15917,
        "uniqueUrlName": null,
        "photos": {
          "small": null,
          "large": null
        },
        "status": null,
        "followed": false
      },
      {
        "name": "Desultory666",
        "id": 15916,
        "uniqueUrlName": null,
        "photos": {
          "small": null,
          "large": null
        },
        "status": null,
        "followed": false
      },
      {
        "name": "allekssandr",
        "id": 15915,
        "uniqueUrlName": null,
        "photos": {
          "small": null,
          "large": null
        },
        "status": null,
        "followed": false
      },
      {
        "name": "Roman13",
        "id": 15914,
        "uniqueUrlName": null,
        "photos": {
          "small": null,
          "large": null
        },
        "status": null,
        "followed": false
      },
      {
        "name": "Roma13",
        "id": 15913,
        "uniqueUrlName": null,
        "photos": {
          "small": null,
          "large": null
        },
        "status": null,
        "followed": false
      },
      {
        "name": "valik1602",
        "id": 15912,
        "uniqueUrlName": null,
        "photos": {
          "small": null,
          "large": null
        },
        "status": null,
        "followed": false
      },
      {
        "name": "konstaphy",
        "id": 15911,
        "uniqueUrlName": null,
        "photos": {
          "small": null,
          "large": null
        },
        "status": null,
        "followed": false
      },
      {
        "name": "julia_evgenievna",
        "id": 15910,
        "uniqueUrlName": null,
        "photos": {
          "small": null,
          "large": null
        },
        "status": null,
        "followed": false
      },
      {
        "name": "newstyle",
        "id": 15909,
        "uniqueUrlName": null,
        "photos": {
          "small": null,
          "large": null
        },
        "status": null,
        "followed": false
      },
      {
        "name": "DaniilS",
        "id": 15908,
        "uniqueUrlName": null,
        "photos": {
          "small": null,
          "large": null
        },
        "status": null,
        "followed": false
      },
      {
        "name": "entempmiss",
        "id": 15907,
        "uniqueUrlName": null,
        "photos": {
          "small": null,
          "large": null
        },
        "status": null,
        "followed": false
      },
      {
        "name": "IgorProverka",
        "id": 15906,
        "uniqueUrlName": null,
        "photos": {
          "small": null,
          "large": null
        },
        "status": null,
        "followed": false
      },
      {
        "name": "pirimb",
        "id": 15905,
        "uniqueUrlName": null,
        "photos": {
          "small": null,
          "large": null
        },
        "status": null,
        "followed": false
      },
      {
        "name": "Stepan40648",
        "id": 15904,
        "uniqueUrlName": null,
        "photos": {
          "small": null,
          "large": null
        },
        "status": "Stepan40648",
        "followed": false
      },
      {
        "name": "valeryaosta",
        "id": 15903,
        "uniqueUrlName": null,
        "photos": {
          "small": null,
          "large": null
        },
        "status": null,
        "followed": false
      },
      {
        "name": "redisko",
        "id": 15902,
        "uniqueUrlName": null,
        "photos": {
          "small": null,
          "large": null
        },
        "status": null,
        "followed": false
      },
      {
        "name": "Loskink",
        "id": 15901,
        "uniqueUrlName": null,
        "photos": {
          "small": null,
          "large": null
        },
        "status": null,
        "followed": false
      },
      {
        "name": "Konsetka",
        "id": 15900,
        "uniqueUrlName": null,
        "photos": {
          "small": null,
          "large": null
        },
        "status": null,
        "followed": false
      },
      {
        "name": "blackskip-notOk",
        "id": 15899,
        "uniqueUrlName": null,
        "photos": {
          "small": null,
          "large": null
        },
        "status": null,
        "followed": false
      },
      {
        "name": "kidhjk",
        "id": 15898,
        "uniqueUrlName": null,
        "photos": {
          "small": null,
          "large": null
        },
        "status": null,
        "followed": false
      },
      {
        "name": "myshka",
        "id": 15897,
        "uniqueUrlName": null,
        "photos": {
          "small": null,
          "large": null
        },
        "status": null,
        "followed": false
      },
      {
        "name": "margot",
        "id": 15896,
        "uniqueUrlName": null,
        "photos": {
          "small": null,
          "large": null
        },
        "status": null,
        "followed": false
      },
      {
        "name": "kap4a149",
        "id": 15895,
        "uniqueUrlName": null,
        "photos": {
          "small": null,
          "large": null
        },
        "status": "ghgdddsdsd sddf",
        "followed": false
      },
      {
        "name": "alametq",
        "id": 15894,
        "uniqueUrlName": null,
        "photos": {
          "small": null,
          "large": null
        },
        "status": null,
        "followed": false
      },
      {
        "name": "ametquia4",
        "id": 15893,
        "uniqueUrlName": null,
        "photos": {
          "small": null,
          "large": null
        },
        "status": null,
        "followed": false
      },
      {
        "name": "alamet",
        "id": 15892,
        "uniqueUrlName": null,
        "photos": {
          "small": null,
          "large": null
        },
        "status": null,
        "followed": false
      },
      {
        "name": "alexAmet",
        "id": 15891,
        "uniqueUrlName": null,
        "photos": {
          "small": null,
          "large": null
        },
        "status": null,
        "followed": false
      },
      {
        "name": "V914",
        "id": 15890,
        "uniqueUrlName": null,
        "photos": {
          "small": null,
          "large": null
        },
        "status": null,
        "followed": false
      },
      {
        "name": "1ametquia",
        "id": 15889,
        "uniqueUrlName": null,
        "photos": {
          "small": null,
          "large": null
        },
        "status": null,
        "followed": false
      },
      {
        "name": "Edward",
        "id": 15888,
        "uniqueUrlName": null,
        "photos": {
          "small": null,
          "large": null
        },
        "status": null,
        "followed": false
      },
      {
        "name": "sid7733",
        "id": 15887,
        "uniqueUrlName": null,
        "photos": {
          "small": null,
          "large": null
        },
        "status": null,
        "followed": false
      },
      {
        "name": "Hammer_UA",
        "id": 15886,
        "uniqueUrlName": null,
        "photos": {
          "small": null,
          "large": null
        },
        "status": null,
        "followed": false
      },
      {
        "name": "RomanL",
        "id": 15885,
        "uniqueUrlName": null,
        "photos": {
          "small": null,
          "large": null
        },
        "status": null,
        "followed": false
      },
      {
        "name": "Gurman",
        "id": 15884,
        "uniqueUrlName": null,
        "photos": {
          "small": null,
          "large": null
        },
        "status": "hle",
        "followed": false
      },
      {
        "name": "Creat1ves",
        "id": 15883,
        "uniqueUrlName": null,
        "photos": {
          "small": null,
          "large": null
        },
        "status": null,
        "followed": false
      },
      {
        "name": "test23",
        "id": 15882,
        "uniqueUrlName": null,
        "photos": {
          "small": null,
          "large": null
        },
        "status": null,
        "followed": false
      },
      {
        "name": "jeekyll",
        "id": 15881,
        "uniqueUrlName": null,
        "photos": {
          "small": null,
          "large": null
        },
        "status": null,
        "followed": false
      },
      {
        "name": "rstrg1234",
        "id": 15880,
        "uniqueUrlName": null,
        "photos": {
          "small": null,
          "large": null
        },
        "status": null,
        "followed": false
      },
      {
        "name": "vadimsent",
        "id": 15879,
        "uniqueUrlName": null,
        "photos": {
          "small": null,
          "large": null
        },
        "status": null,
        "followed": false
      },
      {
        "name": "vadimsen",
        "id": 15878,
        "uniqueUrlName": null,
        "photos": {
          "small": null,
          "large": null
        },
        "status": null,
        "followed": false
      },
      {
        "name": "IlyaB",
        "id": 15877,
        "uniqueUrlName": null,
        "photos": {
          "small": null,
          "large": null
        },
        "status": null,
        "followed": false
      },
      {
        "name": "Valtika",
        "id": 15876,
        "uniqueUrlName": null,
        "photos": {
          "small": null,
          "large": null
        },
        "status": null,
        "followed": false
      },
      {
        "name": "natali222",
        "id": 15875,
        "uniqueUrlName": null,
        "photos": {
          "small": null,
          "large": null
        },
        "status": null,
        "followed": false
      },
      {
        "name": "mig-it",
        "id": 15874,
        "uniqueUrlName": null,
        "photos": {
          "small": null,
          "large": null
        },
        "status": null,
        "followed": false
      },
      {
        "name": "vetchinator",
        "id": 15873,
        "uniqueUrlName": null,
        "photos": {
          "small": null,
          "large": null
        },
        "status": null,
        "followed": false
      },
      {
        "name": "damagem",
        "id": 15872,
        "uniqueUrlName": null,
        "photos": {
          "small": null,
          "large": null
        },
        "status": "Who am I?",
        "followed": false
      },
      {
        "name": "pashkevich_0",
        "id": 15871,
        "uniqueUrlName": null,
        "photos": {
          "small": null,
          "large": null
        },
        "status": null,
        "followed": false
      },
      {
        "name": "DenisDvB",
        "id": 15870,
        "uniqueUrlName": null,
        "photos": {
          "small": null,
          "large": null
        },
        "status": null,
        "followed": false
      },
      {
        "name": "indiraBad",
        "id": 15869,
        "uniqueUrlName": null,
        "photos": {
          "small": null,
          "large": null
        },
        "status": null,
        "followed": false
      },
      {
        "name": "mlary",
        "id": 15868,
        "uniqueUrlName": null,
        "photos": {
          "small": null,
          "large": null
        },
        "status": null,
        "followed": false
      },
      {
        "name": "Senseyka__",
        "id": 15867,
        "uniqueUrlName": null,
        "photos": {
          "small": null,
          "large": null
        },
        "status": null,
        "followed": false
      },
      {
        "name": "Pavlik228",
        "id": 15866,
        "uniqueUrlName": null,
        "photos": {
          "small": null,
          "large": null
        },
        "status": null,
        "followed": false
      },
      {
        "name": "nikita-minov",
        "id": 15865,
        "uniqueUrlName": null,
        "photos": {
          "small": null,
          "large": null
        },
        "status": "я хочу какать da",
        "followed": false
      },
      {
        "name": "nikitaminov",
        "id": 15864,
        "uniqueUrlName": null,
        "photos": {
          "small": null,
          "large": null
        },
        "status": null,
        "followed": false
      },
      {
        "name": "starig",
        "id": 15863,
        "uniqueUrlName": null,
        "photos": {
          "small": null,
          "large": null
        },
        "status": null,
        "followed": false
      },
      {
        "name": "ametquia2",
        "id": 15862,
        "uniqueUrlName": null,
        "photos": {
          "small": null,
          "large": null
        },
        "status": null,
        "followed": false
      },
      {
        "name": "ametquia1",
        "id": 15861,
        "uniqueUrlName": null,
        "photos": {
          "small": null,
          "large": null
        },
        "status": null,
        "followed": false
      },
      {
        "name": "KKK",
        "id": 15860,
        "uniqueUrlName": null,
        "photos": {
          "small": null,
          "large": null
        },
        "status": null,
        "followed": false
      },
      {
        "name": "muzyk0",
        "id": 15859,
        "uniqueUrlName": null,
        "photos": {
          "small": null,
          "large": null
        },
        "status": null,
        "followed": false
      },
      {
        "name": "Arseqpage",
        "id": 15858,
        "uniqueUrlName": null,
        "photos": {
          "small": null,
          "large": null
        },
        "status": null,
        "followed": false
      },
      {
        "name": "OlejaUA",
        "id": 15857,
        "uniqueUrlName": null,
        "photos": {
          "small": null,
          "large": null
        },
        "status": null,
        "followed": false
      },
      {
        "name": "VitaliyGureyev",
        "id": 15856,
        "uniqueUrlName": null,
        "photos": {
          "small": null,
          "large": null
        },
        "status": null,
        "followed": false
      },
      {
        "name": "biralan",
        "id": 15855,
        "uniqueUrlName": null,
        "photos": {
          "small": null,
          "large": null
        },
        "status": null,
        "followed": false
      },
      {
        "name": "krevedko2000",
        "id": 15854,
        "uniqueUrlName": null,
        "photos": {
          "small": null,
          "large": null
        },
        "status": "ищу котлету",
        "followed": false
      },
      {
        "name": "krevedko",
        "id": 15853,
        "uniqueUrlName": null,
        "photos": {
          "small": null,
          "large": null
        },
        "status": null,
        "followed": false
      },
      {
        "name": "Pennywise",
        "id": 15852,
        "uniqueUrlName": null,
        "photos": {
          "small": "https://social-network.samuraijs.com/activecontent/images/users/15852/user-small.jpg?v=1",
          "large": "https://social-network.samuraijs.com/activecontent/images/users/15852/user.jpg?v=1"
        },
        "status": "<!--REACT&REDUX-->",
        "followed": false
      },
      {
        "name": "TolikSergiychuk",
        "id": 15851,
        "uniqueUrlName": null,
        "photos": {
          "small": null,
          "large": null
        },
        "status": null,
        "followed": false
      }
    ]
  }
